coinprice/__init__.py
coinprice/cli.py
coinprice/main.py
coinprice/api/__init__.py
coinprice/api/exchanges.py
coinprice/api/fragment.py
coinprice/app/__init__.py
coinprice/app/fragment.py
coinprice/app/tracker.py
coinprice/app/utils.py
coinprice-2025.1.0.dist-info/LICENSE
coinprice-2025.1.0.dist-info/METADATA
coinprice-2025.1.0.dist-info/WHEEL
coinprice-2025.1.0.dist-info/entry_points.txt
coinprice-2025.1.0.dist-info/top_level.txt
coinprice-2025.1.0.dist-info/RECORD
