Metadata-Version: 2.1
Name: coinprice
Version: 2025.1.0
Summary: Coinprice is a command-line tool for tracking cryptocurrency prices across multiple exchanges.
Home-page: https://github.com/bohd4nx/coinprice
Author: Bohdan (bohd4nx)
Author-email: Bohd4n@proton.me
License: MIT
Project-URL: Documentation, https://github.com/bohd4nx/coinprice/blob/main/README.md
Project-URL: Source, https://github.com/bohd4nx/coinprice
Project-URL: Bug Tracker, https://github.com/bohd4nx/coinprice/issues
Keywords: cryptocurrency,crypto,coinprice,price,tracking,prices,finance,binance,coin,exchange,crypto-tracking
Classifier: Development Status :: 5 - Production/Stable
Classifier: Development Status :: 3 - Alpha
Classifier: Intended Audience :: Developers
Classifier: Intended Audience :: Financial and Insurance Industry
Classifier: Topic :: Software Development :: Libraries :: Python Modules
Classifier: Programming Language :: Python :: 3.9
Classifier: Programming Language :: Python :: 3.10
Classifier: Programming Language :: Python :: 3.11
Classifier: License :: OSI Approved :: MIT License
Classifier: Operating System :: OS Independent
Requires-Python: >=3.9
License-File: LICENSE
Requires-Dist: requests
Requires-Dist: rich
Requires-Dist: colorama
Requires-Dist: beautifulsoup4
Requires-Dist: packaging
